flask_profile/__init__.py
flask_profile/static/css/profiler.css
flask_profile/static/img/asc.gif
flask_profile/static/img/bg.gif
flask_profile/static/img/desc.gif
flask_profile/static/img/profile.png
flask_profile/static/js/jquery.js
flask_profile/static/js/jquery.tablesorter.js
flask_profile/static/js/profiler.js
flask_profile/templates/_profile/profiler.html
Flask_Profile-0.2.dist-info/DESCRIPTION.rst
Flask_Profile-0.2.dist-info/METADATA
Flask_Profile-0.2.dist-info/metadata.json
Flask_Profile-0.2.dist-info/RECORD
Flask_Profile-0.2.dist-info/top_level.txt
Flask_Profile-0.2.dist-info/WHEEL
